src/__init__.py
src/cli.py
src/migrate/__init__.py
src/migrate/elastic.py
src/sync.py
src/utils.py
scanner_cli-0.1.0rc10.dist-info/METADATA
scanner_cli-0.1.0rc10.dist-info/WHEEL
scanner_cli-0.1.0rc10.dist-info/entry_points.txt
scanner_cli-0.1.0rc10.dist-info/RECORD
