Metadata-Version: 2.3
Name: scanner-cli
Version: 0.1.0rc10
Summary: Python command-line interface for Scanner API
Author: Scanner, Inc.
Author-email: support@scanner.dev
Requires-Python: >=3.10,<4.0
Classifier: Programming Language :: Python :: 3
Classifier: Programming Language :: Python :: 3.10
Classifier: Programming Language :: Python :: 3.11
Classifier: Programming Language :: Python :: 3.12
Classifier: Programming Language :: Python :: 3.13
Requires-Dist: PyYAML (>=6.0.2,<7.0.0)
Requires-Dist: click (>=8.1.7,<9.0.0)
Requires-Dist: scanner-client (>=0.1.0rc10,<0.2.0)
